{
    "books":[
        {
            "title": "Just enough research",
            "img": "https://images-na.ssl-images-amazon.com/images/S/compressed.photo.goodreads.com/books/1379351795i/17236175.jpg",
            "author": "Erica Hall",
            "rating": "",
            "status": "to read",
            "link": "https://www.goodreads.com/book/show/17236175-just-enough-research"
        },
        {
            "title": "Rework",
            "img": "https://images-na.ssl-images-amazon.com/images/S/compressed.photo.goodreads.com/books/1391275636i/6732019.jpg",
            "author": "Jason Fried",
            "rating": "",
            "status": "to read",
            "link": "https://www.goodreads.com/book/show/6732019-rework"
        },
        {
            "title": "Looking for Alaska",
            "img": "https://images-na.ssl-images-amazon.com/images/S/compressed.photo.goodreads.com/books/1652042180i/99561.jpg",
            "author": "John Green",
            "rating": "",
            "status": "reading",
            "link": "https://www.goodreads.com/book/show/99561.Looking_for_Alaska"
        },
        {
            "title": "The courage to be disliked",
            "img": "https://images-na.ssl-images-amazon.com/images/S/compressed.photo.goodreads.com/books/1545421684i/43306206.jpg",
            "author": "Ichiro Kishimi",
            "rating": "",
            "status": "reading",
            "link": "https://www.goodreads.com/book/show/43306206-the-courage-to-be-disliked"
        },
        {
            "title": "Sorrounded by idiots",
            "img": "https://www.notion.so/image/https%3A%2F%2Fm.media-amazon.com%2Fimages%2FW%2FMEDIAX_792452-T2%2Fimages%2FI%2F71K7nN6Mu%2BL._AC_UF1000%2C1000_QL80_.jpg?id=8a095f7f-05d9-4ad6-b7a2-dc3175d9e772&table=block&spaceId=44d494cf-786e-496c-b18a-aae3998d8aa5&width=600&userId=01bceef2-866d-47c1-87fa-533e2e16d10f&cache=v2",
            "author": "Thomas Erikson",
            "rating": "3/5",
            "status": "read",
            "link": "https://www.goodreads.com/book/show/39101777-surrounded-by-idiots"
        },
        
        {
            "title": "A hundred years old man who climbed out of the window and disappeared",
            "img": "https://images-na.ssl-images-amazon.com/images/S/compressed.photo.goodreads.com/books/1510447566i/36578942.jpg",
            "author": "Jonas Jonasson",
            "rating": "4/5",
            "status": "read",
            "link": "https://www.goodreads.com/book/show/36578942-the-100-year-old-man-who-climbed-out-the-window-and-disappeared"
        },
        {
            "title": "Why has nobody told me this before?",
            "img": "https://images-na.ssl-images-amazon.com/images/S/compressed.photo.goodreads.com/books/1670001084i/58536046.jpg",
            "author": "Julie Smith",
            "rating": "4/5",
            "status": "read",
            "link": "https://www.goodreads.com/book/show/58536046-why-has-nobody-told-me-this-before"
        },
        {
            "title": "About face",
            "img": "https://images-na.ssl-images-amazon.com/images/S/compressed.photo.goodreads.com/books/1407706749i/18737922.jpg",
            "author": "Allan Cooper",
            "rating": "3.5/5",
            "status": "read",
            "link": "https://www.goodreads.com/book/show/18737922-about-face"
        },
        {
            "title": "Mayflies",
            "img": "https://images-na.ssl-images-amazon.com/images/S/compressed.photo.goodreads.com/books/1598771531i/50162215.jpg",
            "author": "Andrew O'Hagan",
            "rating": "4/5",
            "status": "read",
            "link": "https://www.goodreads.com/book/show/50162215-mayflies"
        },
        {
            "title": "The people we keep",
            "img": "https://images-na.ssl-images-amazon.com/images/S/compressed.photo.goodreads.com/books/1625673640i/55711726.jpg",
            "author": "Allison Larkin",
            "rating": "4.5/5",
            "status": "read",
            "link": "https://www.goodreads.com/book/show/55711726-the-people-we-keep"
        },
        {
            "title": "A man called Ove",
            "img": "https://images-na.ssl-images-amazon.com/images/S/compressed.photo.goodreads.com/books/1405259930i/18774964.jpg",
            "author": "Fredrik Backman",
            "rating": "5/5",
            "status": "read",
            "link": "https://www.goodreads.com/book/show/18774964-a-man-called-ove"
        }
    ]
}